FunkMan.ini
FunkMan.py
LICENSE
MANIFEST.in
README.md
setup.py
funkman/__init__.py
funkman/funkman.py
funkman.egg-info/PKG-INFO
funkman.egg-info/SOURCES.txt
funkman.egg-info/dependency_links.txt
funkman.egg-info/requires.txt
funkman.egg-info/top_level.txt
funkman/funkbot/__init__.py
funkman/funkbot/funkbot.py
funkman/funkplot/__init__.py
funkman/funkplot/funkplot.py
funkman/funksock/__init__.py
funkman/funksock/funksock.py
funkman/utils/__init__.py
funkman/utils/tests.py
funkman/utils/utils.py