Metadata-Version: 2.1
Name: funkman
Version: 0.7.2
Summary: Interface between DCS/MOOSE and Discord via an UDP socket.
Author: funkyfranky
License-File: LICENSE
